exaroton/__init__.py
exaroton/exaroton.py
exaroton/types.py
README.md
exaroton-0.0.7.dist-info/LICENSE
exaroton-0.0.7.dist-info/METADATA
exaroton-0.0.7.dist-info/WHEEL
exaroton-0.0.7.dist-info/RECORD
