Metadata-Version: 2.1
Name: exaroton
Version: 0.0.7
Summary: Python API wrapper for exaroton
Home-page: https://github.com/ColinShark/exaroton
License: MIT
Author: Colin
Author-email: colin@colinshark.de
Requires-Python: >=3.9,<4.0
Classifier: Development Status :: 3 - Alpha
Classifier: License :: OSI Approved :: MIT License
Classifier: Natural Language :: English
Classifier: Operating System :: OS Independent
Classifier: Programming Language :: Python :: 3
Classifier: Programming Language :: Python :: 3.9
Classifier: Programming Language :: Python :: 3.10
Classifier: Programming Language :: Python :: 3.11
Classifier: Programming Language :: Python :: 3.12
Classifier: Programming Language :: Python :: 3.13
Classifier: Programming Language :: Python :: 3 :: Only
Classifier: Topic :: Games/Entertainment
Classifier: Topic :: Internet
Requires-Dist: requests (>=2.28.0,<3.0.0)
Project-URL: Repository, https://github.com/ColinShark/exaroton
